{"9Pj4zcBd4QDpJHrFikFJmw==":"logotipo%20grc-90x61.png","6Zz2nyclF4Na3OH7bbg9wQ==":"logotipo%20grc-240x164.png","qpMrmp/dOxJmnz69kSoNcA==":"mbr-1920x952.jpg","lphdiQP6xNszOMftuMEUNw==":"logotipo%20grc-200x200.png","PSsb6bO4xWdiRY3g/vV4Yw==":"finca_grc-1048x699.jpg","JmYMI5UAmyyPKwHcEeAtJA==":"finca_grc-868x579.jpg","ePqZGegpm0LBpFAOtf3iWA==":"mbr-868x579.jpg","c/sOIG8xYPHfCVybD7Jzkw==":"las_nubes_grc-556x371.jpg","7+T4l3pzCOuN7AiwR45yLA==":"mbr-1920x1280.jpg","vYN4ex0oVmNVAGFJa9pC1Q==":"mbr-1-868x579.jpg","NkHN5RNwpiwEwH5JKxr4NA==":"mbr-1-1920x1280.jpg","BYv9zhshO25qnD2N7pjB1g==":"mbr-2-1920x1280.jpg","kOSxXdyyPClwuhzcB6NkuA==":"mbr-1920x1215.jpg","jRZJ4GM3umanVIRFZ3wQvA==":"bebidas_grc-900x600.jpg","/5XWYEg6Q+gsmgAP08vi8g==":"mbr-900x593.jpg","g4d2EsHmlFEnnZWp17WZVw==":"mbr-900x506.jpg","vKHyFItn9whSMIJM8jAcgg==":"mbr-900x600.jpg","o2AN9Z3TfEW75I7ySINZ5g==":"mbr-1-900x600.jpg","48Axk4CLC2HrSslhX0exUQ==":"mbr-2-900x600.jpg","o4L95vsksivH3eWj0cGpuw==":"mbr-3-900x600.jpg","5yErOh+85AL/CdPi0xWjCQ==":"mbr-1920x1281.jpg","lGSprBCZV5m3KQW8+F7M+w==":"mbr-1920x1281.jpeg","ny40gyhz7BeKZ7LSjqEeTw==":"mbr-1920x1280.jpeg","Yt4eWiaNzXeNZw/SEiSdgQ==":"mbr-1-1920x1280.jpeg","i935De+5ROZS1J3jPm5TAg==":"mbr-2-1920x1280.jpeg","YAIBYcE/dAZ3womIfTYVtA==":"mbr-3-1920x1280.jpeg","kgOIr5ZPZfOjbueQIxDEkQ==":"mbr-4-1920x1280.jpeg","yAjQlmZWGuF2cs9mWZCUoQ==":"tre-fratelli-225x225.jpg","i/EVdUDAMI4kQ70r3hMiTQ==":"11053302_832646470188777_8187298565504294698_n-242x242.jpg","4dZHsgtS1FCiqu9V53fRbg==":"cafe%CC%81-1280x720.jpg","AACyTRylM++iSFtFwW7rAA==":"woman-sitting-on-bar-chair-near-barista-2506993-900x598.jpeg"}